eox_tagging/__init__.py
eox_tagging/admin.py
eox_tagging/api_schema.py
eox_tagging/apps.py
eox_tagging/constants.py
eox_tagging/edxapp_accessors.py
eox_tagging/forms.py
eox_tagging/models.py
eox_tagging/urls.py
eox_tagging/validators.py
eox_tagging/views.py
eox_tagging/api/__init__.py
eox_tagging/api/urls.py
eox_tagging/api/v1/__init__.py
eox_tagging/api/v1/fields.py
eox_tagging/api/v1/filters.py
eox_tagging/api/v1/pagination.py
eox_tagging/api/v1/permissions.py
eox_tagging/api/v1/routers.py
eox_tagging/api/v1/serializers.py
eox_tagging/api/v1/viewset.py
eox_tagging/api/v1/test/__init__.py
eox_tagging/api/v1/test/test_filters.py
eox_tagging/api/v1/test/test_permissions.py
eox_tagging/api/v1/test/test_routers.py
eox_tagging/api/v1/test/test_viewset.py
eox_tagging/edxapp_wrappers/__init__.py
eox_tagging/edxapp_wrappers/bearer_authentication.py
eox_tagging/edxapp_wrappers/course_overview.py
eox_tagging/edxapp_wrappers/enrollments.py
eox_tagging/edxapp_wrappers/backends/__init__.py
eox_tagging/edxapp_wrappers/backends/bearer_authentication_i_v1.py
eox_tagging/edxapp_wrappers/backends/bearer_authentication_i_v1_test.py
eox_tagging/edxapp_wrappers/backends/course_overview_i_v1.py
eox_tagging/edxapp_wrappers/backends/course_overview_i_v1_test.py
eox_tagging/edxapp_wrappers/backends/enrollment_i_v1.py
eox_tagging/edxapp_wrappers/backends/enrollment_l_v1.py
eox_tagging/edxapp_wrappers/backends/enrollment_l_v1_test.py
eox_tagging/edxapp_wrappers/tests/__init__.py
eox_tagging/edxapp_wrappers/tests/integration/__init__.py
eox_tagging/edxapp_wrappers/tests/integration/test_backends.py
eox_tagging/migrations/0001_initial.py
eox_tagging/migrations/0002_auto_20200630_1333.py
eox_tagging/migrations/0003_auto_20200707_1549.py
eox_tagging/migrations/0004_tag_target_index.py
eox_tagging/migrations/__init__.py
eox_tagging/settings/__init__.py
eox_tagging/settings/common.py
eox_tagging/settings/production.py
eox_tagging/settings/test.py
eox_tagging/test/__init__.py
eox_tagging-9.3.2.dist-info/licenses/AUTHORS.txt
eox_tagging-9.3.2.dist-info/licenses/LICENSE.txt
eox_tagging-9.3.2.dist-info/METADATA
eox_tagging-9.3.2.dist-info/WHEEL
eox_tagging-9.3.2.dist-info/entry_points.txt
eox_tagging-9.3.2.dist-info/top_level.txt
eox_tagging-9.3.2.dist-info/RECORD
